{
  "#World Tourism Organization #World Trade Organization #World Terror Order என்பதன் சொற்சுருக்கம் ஆகும். இது ஐக்கிய நாட்டு சபையால்(ஐநா)பயன்படுத்தப்படும்": {
    "default": [
      "WTO"
    ]
  },
  "#நடுநிலைமை தாங்குதல்": {
    "பெயர்ச்சொல்": [
      "abstention"
    ]
  },
  "#ஒழுங்கற்ற": {
    "default": [
      "at sixes and sevens"
    ]
  },
  "#உடன்பாடற்ற நிலையில்": {
    "default": [
      "at sixes and sevens"
    ]
  },
  "#கடுந்துயரம் விளைவிக்கும்": {
    "default": [
      "calamitous"
    ]
  },
  "#வேட்டெஃகக் காயம்": {
    "default": [
      "firearms wound"
    ]
  },
  "# முதன்மையான": {
    "default": [
      "high-profile"
    ]
  },
  "# உறங்கச் செல்லுதல்": {
    "default": [
      "hit the sack"
    ]
  },
  "# மொழியிடை": {
    "default": [
      "inter-language"
    ]
  },
  "# குலுக்குதல்": {
    "default": [
      "jounce"
    ]
  },
  "# குலுக்கல் நிறைந்த": {
    "default": [
      "jouncy"
    ]
  },
  "# சட்டவதிகார வரம்பு": {
    "default": [
      "jurisdiction"
    ]
  },
  "# உரையைக் குரலாக்குதல்": {
    "default": [
      "text to voice"
    ]
  },
  "# காண்பி.": {
    "வினைச்சொல்": [
      "show"
    ]
  },
  "#துணைக்கோள் செய்தித்தொடர்பு:": {
    "default": [
      "satellite communications"
    ]
  },
  "# பன்மொழி": {
    "default": [
      "polyglot"
    ]
  }
}